django_csv/__init__.py
django_csv/admin.py
django_csv/apps.py
django_csv/csv.py
django_csv/migrations/0001_initial.py
django_csv/migrations/0002_swap_csv_download_columns_field_to_textfield.py
django_csv/migrations/__init__.py
django_csv/models.py
django_csv/s3.py
django_csv/settings.py
django_csv/sftp.py
django_csv/types.py
django_csv/views.py
django_csv_downloads-1.5.0.dist-info/METADATA
django_csv_downloads-1.5.0.dist-info/WHEEL
django_csv_downloads-1.5.0.dist-info/licenses/LICENSE
django_csv_downloads-1.5.0.dist-info/RECORD
