Metadata-Version: 2.4
Name: django-csv-downloads
Version: 1.5.0
Summary: Django app for enabling and tracking CSV downloads
License: MIT
License-File: LICENSE
Author: YunoJuno
Author-email: code@yunojuno.com
Maintainer: YunoJuno
Maintainer-email: code@yunojuno.com
Requires-Python: >=3.12,<4.0
Classifier: Development Status :: 4 - Beta
Classifier: Environment :: Web Environment
Classifier: Framework :: Django
Classifier: Framework :: Django :: 5.2
Classifier: Framework :: Django :: 6.0
Classifier: License :: OSI Approved :: MIT License
Classifier: Operating System :: OS Independent
Classifier: Programming Language :: Python :: 3
Classifier: Programming Language :: Python :: 3.12
Classifier: Programming Language :: Python :: 3.13
Classifier: Programming Language :: Python :: 3.14
Classifier: Programming Language :: Python :: 3 :: Only
Provides-Extra: s3
Provides-Extra: sftp
Provides-Extra: test
Requires-Dist: boto3 ; extra == "s3" or extra == "test"
Requires-Dist: django (>=5.2,<7.0)
Requires-Dist: paramiko ; extra == "sftp" or extra == "test"
Project-URL: Documentation, https://github.com/yunojuno/django-csv-downloads
Project-URL: Homepage, https://github.com/yunojuno/django-csv-downloads
Project-URL: Repository, https://github.com/yunojuno/django-csv-downloads
